cellection/__init__.py
cellection/evaluator.py
cellection/loss.py
cellection/model.py
cellection/train.py
cellection/utils.py
cellection-0.1.3.dist-info/licenses/LICENSE
cellection-0.1.3.dist-info/METADATA
cellection-0.1.3.dist-info/WHEEL
cellection-0.1.3.dist-info/top_level.txt
cellection-0.1.3.dist-info/RECORD
