Metadata-Version: 2.4
Name: cellection
Version: 0.1.3
Summary: Predicting emergent phenotypes from single cell populations using CELLECTION
Home-page: https://github.com/quon-titative-biology/CELLECTION
Author: Hongru Hu
Author-email: Hongru Hu <hrhu.compbio@gmail.com>
Maintainer-email: Hongru Hu <hrhu.compbio@gmail.com>
License: MIT
Project-URL: Homepage, https://github.com/quon-titative-biology/CELLECTION
Project-URL: Documentation, https://github.com/quon-titative-biology/CELLECTION#readme
Project-URL: Repository, https://github.com/quon-titative-biology/CELLECTION
Project-URL: Bug Tracker, https://github.com/quon-titative-biology/CELLECTION/issues
Keywords: deep-learning,bioinformatics,machine-learning,multiple-instance-learning,pointnet
Classifier: Development Status :: 3 - Alpha
Classifier: Intended Audience :: Science/Research
Classifier: License :: OSI Approved :: MIT License
Classifier: Operating System :: OS Independent
Classifier: Programming Language :: Python :: 3
Classifier: Programming Language :: Python :: 3.8
Classifier: Programming Language :: Python :: 3.9
Classifier: Programming Language :: Python :: 3.10
Classifier: Programming Language :: Python :: 3.11
Classifier: Topic :: Scientific/Engineering :: Artificial Intelligence
Classifier: Topic :: Scientific/Engineering :: Bio-Informatics
Requires-Python: >=3.8
License-File: LICENSE
Requires-Dist: torch==2.4.1
Requires-Dist: numpy>=1.21.0
Requires-Dist: scipy>=1.7.0
Requires-Dist: scikit-learn>=1.0.0
Requires-Dist: matplotlib>=3.5.0
Requires-Dist: seaborn>=0.11.0
Requires-Dist: pandas>=1.3.0
Requires-Dist: tqdm>=4.60.0
Requires-Dist: scanpy==1.10.3
Requires-Dist: anndata==0.10.9
Provides-Extra: dev
Requires-Dist: pytest>=6.0; extra == "dev"
Requires-Dist: pytest-cov>=2.0; extra == "dev"
Requires-Dist: black>=21.0; extra == "dev"
Requires-Dist: flake8>=3.8; extra == "dev"
Provides-Extra: full
Requires-Dist: scanpy==1.10.3; extra == "full"
Requires-Dist: anndata==0.10.9; extra == "full"
Requires-Dist: scvi-tools>=0.20.0; extra == "full"
Dynamic: author
Dynamic: home-page
Dynamic: license-file
Dynamic: requires-python
